{
	"name": "VehicleStockCSV",
	"properties": {
		"linkedServiceName": {
			"referenceName": "AutolyticaBlobProd",
			"type": "LinkedServiceReference"
		},
		"annotations": [],
		"type": "DelimitedText",
		"typeProperties": {
			"location": {
				"type": "AzureBlobStorageLocation",
				"container": "autolytica"
			},
			"columnDelimiter": ",",
			"escapeChar": "\\",
			"firstRowAsHeader": true,
			"quoteChar": "\""
		},
		"schema": [
			{
				"name": "Client ID",
				"type": "String"
			},
			{
				"name": "Dealer ID",
				"type": "String"
			},
			{
				"name": "Vehicle Type",
				"type": "String"
			},
			{
				"name": "Registration Number",
				"type": "String"
			},
			{
				"name": "Stock Number",
				"type": "String"
			},
			{
				"name": "Group Date in Stock",
				"type": "String"
			},
			{
				"name": "Dealership Date In Stock",
				"type": "String"
			},
			{
				"name": "Status",
				"type": "String"
			},
			{
				"name": "New Or Used",
				"type": "String"
			},
			{
				"name": "Chassis",
				"type": "String"
			},
			{
				"name": "Registration Date",
				"type": "String"
			},
			{
				"name": "Make",
				"type": "String"
			},
			{
				"name": "Model",
				"type": "String"
			},
			{
				"name": "Derivative",
				"type": "String"
			},
			{
				"name": "Trim",
				"type": "String"
			},
			{
				"name": "Engine Size",
				"type": "String"
			},
			{
				"name": "Bodystyle",
				"type": "String"
			},
			{
				"name": "Odometer",
				"type": "String"
			},
			{
				"name": "Odometer Type",
				"type": "String"
			},
			{
				"name": "FuelType",
				"type": "String"
			},
			{
				"name": "Transmission",
				"type": "String"
			},
			{
				"name": "Generic Colour",
				"type": "String"
			},
			{
				"name": "Doors",
				"type": "String"
			},
			{
				"name": "Stock Value",
				"type": "String"
			},
			{
				"name": "Vat",
				"type": "String"
			},
			{
				"name": "Source",
				"type": "String"
			},
			{
				"name": "Vehicle Category Code",
				"type": "String"
			},
			{
				"name": "Retail Price",
				"type": "String"
			},
			{
				"name": "Purchaser ID",
				"type": "String"
			},
			{
				"name": "Supplier",
				"type": "String"
			},
			{
				"name": "Group Purchase Date",
				"type": "String"
			},
			{
				"name": "Available Date",
				"type": "String"
			},
			{
				"name": "Progress Code",
				"type": "String"
			},
			{
				"name": "Reconditioning",
				"type": "String"
			},
			{
				"name": "Transport Costs",
				"type": "String"
			},
			{
				"name": "Adjusted Stock Value",
				"type": "String"
			},
			{
				"name": "Received Date",
				"type": "String"
			},
			{
				"name": "Purchase Account",
				"type": "String"
			},
			{
				"name": "Quarantine Status",
				"type": "String"
			}
		]
	},
	"type": "Microsoft.DataFactory/factories/datasets"
}